intentai/__init__.py
intentai/intentai.py
intentai_kiran-1.0.1.dist-info/METADATA
intentai_kiran-1.0.1.dist-info/WHEEL
intentai_kiran-1.0.1.dist-info/top_level.txt
intentai_kiran-1.0.1.dist-info/RECORD
