Metadata-Version: 2.4
Name: intentai-kiran
Version: 1.0.1
Summary: IntentAI SDK
Author: Kiran Shetty
Requires-Python: >=3.8
